{
  "generated_at": "2026-05-09",
  "total_rounds": 1223,
  "all_time": {
    "min_sum": 48,
    "min_sum_round": 312,
    "max_sum": 238,
    "max_sum_round": 196,
    "median": 138
  },
  "latest_round": {
    "draw_no": 1223,
    "sum": 158,
    "numbers": [
      16,
      18,
      20,
      32,
      33,
      39
    ],
    "range": "151~200"
  },
  "periods": [
    {
      "label": "2개월",
      "round_count": 9,
      "avg_sum": 138,
      "top_range": "151~200",
      "top_range_count": 4,
      "prev_period_diff": {
        "range": "151~200",
        "diff": 0
      },
      "streak": {
        "range": "151~200",
        "count": 1
      },
      "ranges": [
        {
          "range": "21~50",
          "count": 0,
          "pct": 0.0,
          "value": 0.0
        },
        {
          "range": "51~100",
          "count": 1,
          "pct": 11.1,
          "value": 0.25
        },
        {
          "range": "101~150",
          "count": 4,
          "pct": 44.4,
          "value": 1.0
        },
        {
          "range": "151~200",
          "count": 4,
          "pct": 44.4,
          "value": 1.0
        },
        {
          "range": "201~257",
          "count": 0,
          "pct": 0.0,
          "value": 0.0
        }
      ],
      "recent_5": [
        {
          "round": 1223,
          "sum": 158,
          "range": "151~200"
        },
        {
          "round": 1222,
          "sum": 127,
          "range": "101~150"
        },
        {
          "round": 1221,
          "sum": 131,
          "range": "101~150"
        },
        {
          "round": 1220,
          "sum": 154,
          "range": "151~200"
        },
        {
          "round": 1219,
          "sum": 130,
          "range": "101~150"
        }
      ]
    },
    {
      "label": "6개월",
      "round_count": 26,
      "avg_sum": 142,
      "top_range": "101~150",
      "top_range_count": 12,
      "prev_period_diff": {
        "range": "101~150",
        "diff": -6
      },
      "streak": {
        "range": "151~200",
        "count": 1
      },
      "ranges": [
        {
          "range": "21~50",
          "count": 0,
          "pct": 0.0,
          "value": 0.0
        },
        {
          "range": "51~100",
          "count": 3,
          "pct": 11.5,
          "value": 0.25
        },
        {
          "range": "101~150",
          "count": 12,
          "pct": 46.2,
          "value": 1.0
        },
        {
          "range": "151~200",
          "count": 10,
          "pct": 38.5,
          "value": 0.8333
        },
        {
          "range": "201~257",
          "count": 1,
          "pct": 3.8,
          "value": 0.0833
        }
      ],
      "recent_5": [
        {
          "round": 1223,
          "sum": 158,
          "range": "151~200"
        },
        {
          "round": 1222,
          "sum": 127,
          "range": "101~150"
        },
        {
          "round": 1221,
          "sum": 131,
          "range": "101~150"
        },
        {
          "round": 1220,
          "sum": 154,
          "range": "151~200"
        },
        {
          "round": 1219,
          "sum": 130,
          "range": "101~150"
        }
      ]
    },
    {
      "label": "1년",
      "round_count": 52,
      "avg_sum": 135,
      "top_range": "101~150",
      "top_range_count": 30,
      "prev_period_diff": {
        "range": "101~150",
        "diff": 3
      },
      "streak": {
        "range": "151~200",
        "count": 1
      },
      "ranges": [
        {
          "range": "21~50",
          "count": 0,
          "pct": 0.0,
          "value": 0.0
        },
        {
          "range": "51~100",
          "count": 7,
          "pct": 13.5,
          "value": 0.2333
        },
        {
          "range": "101~150",
          "count": 30,
          "pct": 57.7,
          "value": 1.0
        },
        {
          "range": "151~200",
          "count": 14,
          "pct": 26.9,
          "value": 0.4667
        },
        {
          "range": "201~257",
          "count": 1,
          "pct": 1.9,
          "value": 0.0333
        }
      ],
      "recent_5": [
        {
          "round": 1223,
          "sum": 158,
          "range": "151~200"
        },
        {
          "round": 1222,
          "sum": 127,
          "range": "101~150"
        },
        {
          "round": 1221,
          "sum": 131,
          "range": "101~150"
        },
        {
          "round": 1220,
          "sum": 154,
          "range": "151~200"
        },
        {
          "round": 1219,
          "sum": 130,
          "range": "101~150"
        }
      ]
    },
    {
      "label": "3년",
      "round_count": 155,
      "avg_sum": 138,
      "top_range": "101~150",
      "top_range_count": 85,
      "prev_period_diff": {
        "range": "101~150",
        "diff": -1
      },
      "streak": {
        "range": "151~200",
        "count": 1
      },
      "ranges": [
        {
          "range": "21~50",
          "count": 0,
          "pct": 0.0,
          "value": 0.0
        },
        {
          "range": "51~100",
          "count": 19,
          "pct": 12.3,
          "value": 0.2235
        },
        {
          "range": "101~150",
          "count": 85,
          "pct": 54.8,
          "value": 1.0
        },
        {
          "range": "151~200",
          "count": 47,
          "pct": 30.3,
          "value": 0.5529
        },
        {
          "range": "201~257",
          "count": 4,
          "pct": 2.6,
          "value": 0.0471
        }
      ],
      "recent_5": [
        {
          "round": 1223,
          "sum": 158,
          "range": "151~200"
        },
        {
          "round": 1222,
          "sum": 127,
          "range": "101~150"
        },
        {
          "round": 1221,
          "sum": 131,
          "range": "101~150"
        },
        {
          "round": 1220,
          "sum": 154,
          "range": "151~200"
        },
        {
          "round": 1219,
          "sum": 130,
          "range": "101~150"
        }
      ]
    },
    {
      "label": "10년",
      "round_count": 515,
      "avg_sum": 139,
      "top_range": "101~150",
      "top_range_count": 281,
      "prev_period_diff": {
        "range": "101~150",
        "diff": 3
      },
      "streak": {
        "range": "151~200",
        "count": 1
      },
      "ranges": [
        {
          "range": "21~50",
          "count": 1,
          "pct": 0.2,
          "value": 0.0036
        },
        {
          "range": "51~100",
          "count": 56,
          "pct": 10.9,
          "value": 0.1993
        },
        {
          "range": "101~150",
          "count": 281,
          "pct": 54.6,
          "value": 1.0
        },
        {
          "range": "151~200",
          "count": 165,
          "pct": 32.0,
          "value": 0.5872
        },
        {
          "range": "201~257",
          "count": 12,
          "pct": 2.3,
          "value": 0.0427
        }
      ],
      "recent_5": [
        {
          "round": 1223,
          "sum": 158,
          "range": "151~200"
        },
        {
          "round": 1222,
          "sum": 127,
          "range": "101~150"
        },
        {
          "round": 1221,
          "sum": 131,
          "range": "101~150"
        },
        {
          "round": 1220,
          "sum": 154,
          "range": "151~200"
        },
        {
          "round": 1219,
          "sum": 130,
          "range": "101~150"
        }
      ]
    }
  ]
}